comping_test/__init__.py
comping_test/base.py
comping_test/demo.py
comping_test/detectors/__init__.py
comping_test/detectors/detectors.py
comping_test/utils/__init__.py
comping_test-0.1.1.dist-info/METADATA
comping_test-0.1.1.dist-info/WHEEL
comping_test-0.1.1.dist-info/top_level.txt
comping_test-0.1.1.dist-info/RECORD
