Metadata-Version: 2.4
Name: comping-test
Version: 0.1.1
Summary: A lightweight concept drift detection library
Author-email: Gyujin Kim <gj.kim@comping.ai>
License: MIT
Requires-Python: >=3.8
